MANIFEST.in
README.rst
setup.py
completion/_wstool
completion/wstool-completion.bash
doc/Makefile
doc/changelog.rst
doc/conf.py
doc/developers_guide.rst
doc/index.rst
doc/make.bat
doc/rosinstall_file_format.rst
doc/wstool_usage.rst
scripts/wstool
src/wstool/__init__.py
src/wstool/__version__.py
src/wstool/cli_common.py
src/wstool/common.py
src/wstool/config.py
src/wstool/config_elements.py
src/wstool/config_yaml.py
src/wstool/helpers.py
src/wstool/multiproject_cli.py
src/wstool/multiproject_cmd.py
src/wstool/ui.py
src/wstool/wstool_cli.py
src/wstool.egg-info/PKG-INFO
src/wstool.egg-info/SOURCES.txt
src/wstool.egg-info/dependency_links.txt
src/wstool.egg-info/requires.txt
src/wstool.egg-info/top_level.txt